botify/__init__.py
botify/api.py
botify/errors.py
botify/models.py
botify_api-0.0.1.dist-info/LICENSE
botify_api-0.0.1.dist-info/METADATA
botify_api-0.0.1.dist-info/WHEEL
botify_api-0.0.1.dist-info/top_level.txt
botify_api-0.0.1.dist-info/RECORD
