Metadata-Version: 2.1
Name: botify-api
Version: 0.0.1
Summary: An API wrapper for the Botify API
Author: Timo
License: MIT
Project-URL: GitHub, https://github.com/timoo4devv/botify-api
Project-URL: Documentation, https://botify-api.readthedocs.io
Keywords: discord,bot,botify,api
Classifier: Development Status :: 5 - Production/Stable
Classifier: License :: OSI Approved :: MIT License
Classifier: Intended Audience :: Developers
Classifier: Operating System :: OS Independent
Classifier: Programming Language :: Python :: 3.9
Classifier: Programming Language :: Python :: 3.10
Classifier: Programming Language :: Python :: 3.11
Classifier: Programming Language :: Python :: 3.12
Classifier: Programming Language :: Python :: 3.13
Requires-Python: >=3.9
License-File: LICENSE
Requires-Dist: httpx
Requires-Dist: python-dotenv
